{"cone_density": "Moderate to compact", "characteristics": "Spicy, earthy, and lightly floral aroma", "farnesene_oil": "0%-1%", "total_oil_composition": "1.6-2.4 mL/100g", "caryophyllene_oil": "10%-12%", "beta_acid_composition": "3%-4%", "yield_amount": "2700-3100 kg/hectare (2410-2770 lbs/acre)", "alpha_acid_composition": "14%-17%", "ease_of_harvest": "Difficult", "seasonal_maturity": "Late", "storability": "Retains 70% alpha acid after 6 months storage at 20 degrees C", "source": "http://www.hopslist.com/hops/bittering-hops/649-bravo", "resistant_to": "Resistant to powdery mildew and verticillium wilt", "co_humulone_composition": "29%-34%", "style_guide": "India Pale Ale", "growth_rate": "Very high", "substitutes": "Columbus, Zeus, Apollo", "cone_size": "Medium", "component": "Bittering / Alpha Hops", "myrcene_oil_composition": "25%-50%", "susceptible_to": "Susceptible to downy mildew", "also_known_as": "", "name": "Bravo", "country": "", "source_id": "649", "humulene_oil_composition": "18%-20%", "purpose": "Bittering"}