{"cone_density": "", "characteristics": "European aroma, similar to Styrian hops", "farnesene_oil": "7.1%", "total_oil_composition": "1.07 mL/100g", "caryophyllene_oil": "6.2%", "beta_acid_composition": "2%-3%", "yield_amount": "630 kg/hectare (560 lbs/acre)", "alpha_acid_composition": "6%-8%", "ease_of_harvest": "", "seasonal_maturity": "Late", "storability": "Retains 79% alpha acid after 6 months storage at 20\u00baC (68\u00baF)", "source": "http://www.hopslist.com/hops/aroma-hops/cekin/", "resistant_to": "Moderately resistant to downy mildew", "co_humulone_composition": "24%", "style_guide": "", "growth_rate": "", "substitutes": "", "cone_size": "", "component": "aroma-hops", "percent_alpha_acids": 0.06, "myrcene_oil_composition": "47.9%", "susceptible_to": "", "also_known_as": "", "name": "Cekin", "country": "Slovenia", "source_id": "cekin", "humulene_oil_composition": "16.5%", "purpose": "Aroma"}