{"cone_density": "Compact", "characteristics": "", "farnesene_oil": "0%-1%", "total_oil_composition": "1.5-3 mL/100g", "caryophyllene_oil": "7%-10%", "beta_acid_composition": "4.2%-5.8%", "yield_amount": "1700-2200 kg/hectare (1520-1970 lbs/acre)", "alpha_acid_composition": "9.5%-14%", "ease_of_harvest": "Difficult", "seasonal_maturity": "Mid", "storability": "Retains 70%-80% alpha acid after 6 months storage at 20 degrees C", "source": "http://www.hopslist.com/hops/dual-purpose-hops/769-nugget", "resistant_to": "Resistant to prunus necrotic ring-spot virus, downy mildew and powdery mildew", "co_humulone_composition": "22%-30%", "style_guide": "India Pale Ale", "growth_rate": "Moderate", "substitutes": "Galena", "cone_size": "Medium to large", "component": "Dual-Purpose Hops", "myrcene_oil_composition": "48%-59%", "susceptible_to": "", "purpose": "Bittering & Aroma", "name": "Nugget", "country": "", "humulene_oil_composition": "12%-22%", "also_known_as": ""}