{"cone_density": "", "characteristics": "", "farnesene_oil": "0.1%", "total_oil_composition": "0.9 mL/100g", "caryophyllene_oil": "10.3%", "beta_acid_composition": "3.3%", "yield_amount": "900 kg/hectare (800 lbs/acre)", "alpha_acid_composition": "4.8%", "ease_of_harvest": "", "seasonal_maturity": "Mid", "storability": "Retains 70% alpha acid after 6 months storage at 20 degrees C", "source": "http://www.hopslist.com/hops/aroma-hops/816-strisselspalter", "resistant_to": "Resistant to verticillium wilt", "co_humulone_composition": "27%", "style_guide": "Lager, Saison, Blonde Ale, Amber Ale, Belgian Ale, Bock, Maibock, Golden Ale, Belgian Pale Ale", "growth_rate": "High to Low", "substitutes": "Mount Hood, Crystal, Hersbrucker", "cone_size": "", "component": "Aroma / Noble Hops", "myrcene_oil_composition": "48%", "susceptible_to": "", "purpose": "Aroma", "name": "Strisselspalter", "country": "France", "humulene_oil_composition": "28%-32%", "also_known_as": ""}